hypercat/__init__.py
hypercat/hypercat.py
hypercat.py-0.1.2.dist-info/DESCRIPTION.rst
hypercat.py-0.1.2.dist-info/METADATA
hypercat.py-0.1.2.dist-info/RECORD
hypercat.py-0.1.2.dist-info/WHEEL
hypercat.py-0.1.2.dist-info/metadata.json
hypercat.py-0.1.2.dist-info/top_level.txt
