Metadata-Version: 2.0
Name: hypercat.py
Version: 0.1.2
Summary: Module for working with Hypercat catalogues
Home-page: https://github.com/thingful/hypercat-py
Author: Pilgrim Beart
Author-email: firstname.lastname@1248.io
License: MIT
Keywords: development hypercat
Platform: UNKNOWN
Classifier: Development Status :: 4 - Beta
Classifier: Intended Audience :: Developers
Classifier: License :: OSI Approved :: MIT License
Classifier: Programming Language :: Python :: 2
Classifier: Programming Language :: Python :: 2.6
Classifier: Programming Language :: Python :: 2.7
Classifier: Programming Language :: Python :: 3
Classifier: Programming Language :: Python :: 3.2
Classifier: Programming Language :: Python :: 3.3
Classifier: Programming Language :: Python :: 3.4
Classifier: Programming Language :: Python :: 3.5
